skribble/__init__.py
skribble/client.py
skribble/client_manager.py
skribble/exceptions.py
skribble/models.py
skribble/auth/__init__.py
skribble/auth/operations.py
skribble/document/__init__.py
skribble/document/operations.py
skribble/seal/__init__.py
skribble/seal/operations.py
skribble/signature_request/__init__.py
skribble/signature_request/operations.py
skribble_sdk-0.17.dist-info/LICENSE
skribble_sdk-0.17.dist-info/METADATA
skribble_sdk-0.17.dist-info/WHEEL
skribble_sdk-0.17.dist-info/top_level.txt
skribble_sdk-0.17.dist-info/RECORD
