Metadata-Version: 2.2
Name: skribble-sdk
Version: 0.17
Summary: A Python SDK for the Skribble API
Author-email: Eric Campos <ec@webix.ch>
License: MIT License
Project-URL: Homepage, https://github.com/LeEricCH/skribble-sdk
Project-URL: Documentation, https://skribblesdk.mintlify.app/
Project-URL: Repository, https://github.com/LeEricCH/skribble-sdk.git
Keywords: skribble,api,sdk
Classifier: Development Status :: 3 - Alpha
Classifier: Intended Audience :: Developers
Classifier: License :: OSI Approved :: MIT License
Classifier: Programming Language :: Python :: 3
Classifier: Programming Language :: Python :: 3.7
Classifier: Programming Language :: Python :: 3.8
Classifier: Programming Language :: Python :: 3.9
Requires-Python: >=3.7
License-File: LICENSE
Requires-Dist: requests
Requires-Dist: pydantic
Provides-Extra: test
Requires-Dist: pytest>=7.0.0; extra == "test"
Requires-Dist: pytest-cov>=4.0.0; extra == "test"
Requires-Dist: pytest-mock>=3.10.0; extra == "test"
Requires-Dist: requests-mock>=1.11.0; extra == "test"
Requires-Dist: python-dotenv>=1.0.0; extra == "test"
